{
  "schemaVersion": 2,
  "gracePeriod": "12h",
  "campaigns": [
    {
      "version": 1,
      "advertiserId": "216c5e8c-434d-4c72-a9c5-3a11343dde48",
      "campaignId": "f93835e7-d229-4d2c-b3ef-1d4cab870c23",
      "startAt": "2025-05-05T04:00:00.000Z",
      "endAt": "2025-05-06T03:59:00.000Z",
      "dailyCap": 20,
      "priority": 1,
      "ptr": 1,
      "metrics": "p3a",
      "geoTargets": [
        "AD",
        "AE",
        "AF",
        "AL",
        "AM",
        "AO",
        "AR",
        "AT",
        "AU",
        "AW",
        "AZ",
        "BA",
        "BB",
        "BD",
        "BE",
        "BF",
        "BG",
        "BH",
        "BI",
        "BJ",
        "BM",
        "BN",
        "BO",
        "BR",
        "BS",
        "BT",
        "BW",
        "BZ",
        "CA",
        "CD",
        "CG",
        "CH",
        "CI",
        "CL",
        "CM",
        "CN",
        "CO",
        "CR",
        "CV",
        "CW",
        "CY",
        "CZ",
        "DE",
        "DJ",
        "DK",
        "DM",
        "DO",
        "DZ",
        "EC",
        "EE",
        "EG",
        "ES",
        "ET",
        "FI",
        "FJ",
        "FO",
        "FR",
        "GA",
        "GB",
        "GD",
        "GE",
        "GF",
        "GG",
        "GH",
        "GI",
        "GM",
        "GN",
        "GP",
        "GR",
        "GT",
        "GU",
        "GY",
        "HK",
        "HN",
        "HR",
        "HT",
        "HU",
        "ID",
        "IE",
        "IL",
        "IM",
        "IN",
        "IQ",
        "IS",
        "IT",
        "JE",
        "JM",
        "JO",
        "KE",
        "KG",
        "KH",
        "KR",
        "KW",
        "KY",
        "KZ",
        "LA",
        "LB",
        "LC",
        "LI",
        "LK",
        "LS",
        "LT",
        "LU",
        "LV",
        "LY",
        "MA",
        "MC",
        "ME",
        "MG",
        "MK",
        "ML",
        "MM",
        "MN",
        "MO",
        "MQ",
        "MR",
        "MT",
        "MU",
        "MV",
        "MW",
        "MX",
        "MY",
        "MZ",
        "NA",
        "NC",
        "NE",
        "NG",
        "NI",
        "NL",
        "NO",
        "NP",
        "NZ",
        "OM",
        "PA",
        "PE",
        "PF",
        "PG",
        "PH",
        "PK",
        "PL",
        "PR",
        "PS",
        "PT",
        "PY",
        "QA",
        "RE",
        "RO",
        "RS",
        "RW",
        "SA",
        "SC",
        "SD",
        "SE",
        "SG",
        "SI",
        "SK",
        "SL",
        "SN",
        "SO",
        "SR",
        "SV",
        "SZ",
        "TG",
        "TH",
        "TN",
        "TO",
        "TR",
        "TT",
        "TW",
        "UG",
        "US",
        "UY",
        "UZ",
        "VC",
        "VI",
        "VN",
        "YE",
        "ZA",
        "ZM",
        "ZW"
      ],
      "creativeSets": [
        {
          "creativeSetId": "9bf1f5ea-d483-4c3f-985e-b6b393dfc7c5",
          "perDay": 20,
          "perMonth": 0,
          "perWeek": 0,
          "totalMax": 20,
          "value": "0",
          "creatives": [
            {
              "creativeInstanceId": "adc083e7-4d46-48db-9190-91b51fb26edc",
              "targetUrl": "https://brave.com/firewall-vpn/?mtm_source=brave-browser&mtm_medium=brave-ntp&mtm_campaign=brave-vpn&mtm_content=adc083e7-4d46-48db-9190-91b51fb26edc&mtm_date=20250505",
              "alt": "Brave VPN - Traveling or on public Wi-Fi? No worries. Protect yourself with Brave VPN. - Try Brave VPN",
              "companyName": "Brave VPN",
              "wallpaper": {
                "type": "image",
                "relativeUrl": "c3c36b39-5907-4229-8aab-0fa36c5671e6.jpg",
                "button": {
                  "image": {
                    "relativeUrl": "adad97aa-b7d4-475c-bd94-d190f91d7366.png"
                  }
                },
                "focalPoint": {
                  "x": 1280,
                  "y": 720
                }
              }
            },
            {
              "creativeInstanceId": "de212377-3b7d-4142-8e75-7d6a1cb6b327",
              "targetUrl": "https://brave.com/firewall-vpn/?mtm_source=brave-browser&mtm_medium=brave-ntp&mtm_campaign=brave-vpn&mtm_content=de212377-3b7d-4142-8e75-7d6a1cb6b327&mtm_date=20250505",
              "alt": "Brave VPN - Traveling or on public Wi-Fi? No worries. Protect yourself with Brave VPN. - Try Brave VPN",
              "companyName": "Brave VPN",
              "wallpaper": {
                "type": "image",
                "relativeUrl": "48f7c565-09ee-48e0-bf2d-d2a6c9ffa5e4.jpg",
                "button": {
                  "image": {
                    "relativeUrl": "adad97aa-b7d4-475c-bd94-d190f91d7366.png"
                  }
                },
                "focalPoint": {
                  "x": 1134,
                  "y": 720
                }
              }
            }
          ]
        }
      ]
    }
  ]
}